celerybeat_status/__init__.py
celerybeat_status/admin.py
celerybeat_status/apps.py
celerybeat_status/helpers.py
celerybeat_status/urls.py
celerybeat_status/views.py
celerybeat_status/templates/celerybeat_status/periodic_tasks_status_list.html
celerybeat_status/templates/celerybeat_status/custom_admin/index.html
celerybeat_status/templates/celerybeat_status/custom_admin/sidebar.html
celerybeat_status/templates/celerybeat_status/custom_admin/sidebar_widgets/actions.html
celerybeat_status/templates/celerybeat_status/custom_admin/sidebar_widgets/statuscheck.html
celerybeat_status/tests/__init__.py
celerybeat_status/tests/test_views.py
celerybeat_status/tests/utils.py
django_celerybeat_status-1.0.1.dist-info/LICENSE.txt
django_celerybeat_status-1.0.1.dist-info/METADATA
django_celerybeat_status-1.0.1.dist-info/WHEEL
django_celerybeat_status-1.0.1.dist-info/top_level.txt
django_celerybeat_status-1.0.1.dist-info/RECORD
